{
  "filename": "H_0262.jpg",
  "filepath": "anime_images/H_0262.jpg",
  "keypoints": [
    {
      "name": "head_top",
      "x": 325.62269389629364,
      "y": 51.886035722494114,
      "confidence": 0.9999754428863525
    },
    {
      "name": "head_center",
      "x": 325.62269389629364,
      "y": 142.76884013414383,
      "confidence": 0.9999754428863525
    },
    {
      "name": "neck",
      "x": 317.34987765550613,
      "y": 256.37234564870596,
      "confidence": 0.9999707341194153
    },
    {
      "name": "left_shoulder",
      "x": 419.48233127593994,
      "y": 256.00259836018085,
      "confidence": 0.9999785423278809
    },
    {
      "name": "right_shoulder",
      "x": 215.21742403507233,
      "y": 256.74209293723106,
      "confidence": 0.9999629259109497
    },
    {
      "name": "left_elbow",
      "x": 441.00101590156555,
      "y": 416.7566624879837,
      "confidence": 0.9802882671356201
    },
    {
      "name": "right_elbow",
      "x": 190.4150277376175,
      "y": 404.57798051834106,
      "confidence": 0.9853213429450989
    },
    {
      "name": "left_wrist",
      "x": 453.39428782463074,
      "y": 544.4859124720097,
      "confidence": 0.9820746779441833
    },
    {
      "name": "right_wrist",
      "x": 166.02915823459625,
      "y": 543.6696905195713,
      "confidence": 0.9921371340751648
    },
    {
      "name": "chest_center",
      "x": 317.34987765550613,
      "y": 406.5728881470859,
      "confidence": 0.9999716281890869
    },
    {
      "name": "waist_center",
      "x": 329.02109041810036,
      "y": 556.7734306454659,
      "confidence": 0.9999640583992004
    },
    {
      "name": "left_hip",
      "x": 382.5995308160782,
      "y": 556.5147752761841,
      "confidence": 0.999964714050293
    },
    {
      "name": "right_hip",
      "x": 275.4426500201225,
      "y": 557.0320860147476,
      "confidence": 0.9999634027481079
    },
    {
      "name": "left_knee",
      "x": 382.525395154953,
      "y": 781.0202324390411,
      "confidence": 0.978996753692627
    },
    {
      "name": "right_knee",
      "x": 263.8995748758316,
      "y": 781.6164684295654,
      "confidence": 0.9776393175125122
    },
    {
      "name": "left_ankle",
      "x": 374.0569865703583,
      "y": 1012.2124564051628,
      "confidence": 0.9878407120704651
    },
    {
      "name": "right_ankle",
      "x": 230.90493351221085,
      "y": 1014.3712008595467,
      "confidence": 0.9867254495620728
    },
    {
      "name": "left_hand",
      "x": 447.8559285402298,
      "y": 591.3380638957024,
      "confidence": 0.9726893305778503
    },
    {
      "name": "right_hand",
      "x": 158.72397780418396,
      "y": 582.6754556298256,
      "confidence": 0.9876214861869812
    },
    {
      "name": "left_foot",
      "x": 454.9354660511017,
      "y": 1061.2040836811066,
      "confidence": 0.9860000014305115
    },
    {
      "name": "right_foot",
      "x": 215.00901520252228,
      "y": 1074.3430228829384,
      "confidence": 0.9802300930023193
    }
  ],
  "confidence": 0.9880829172975877,
  "image_width": 610,
  "image_height": 1109,
  "keypoint_names": [
    "head_top",
    "head_center",
    "neck",
    "left_shoulder",
    "right_shoulder",
    "left_elbow",
    "right_elbow",
    "left_wrist",
    "right_wrist",
    "chest_center",
    "waist_center",
    "left_hip",
    "right_hip",
    "left_knee",
    "right_knee",
    "left_ankle",
    "right_ankle",
    "left_hand",
    "right_hand",
    "left_foot",
    "right_foot"
  ],
  "labeled_at": "2026-01-22T18:33:16.804361"
}