{
  "filename": "H_0249.jpg",
  "filepath": "anime_images/H_0249.jpg",
  "keypoints": [
    {
      "name": "head_top",
      "x": 218.9128074645996,
      "y": 6.441028594970703,
      "confidence": 0.9999874830245972
    },
    {
      "name": "head_center",
      "x": 218.9128074645996,
      "y": 51.49189472198486,
      "confidence": 0.9999874830245972
    },
    {
      "name": "neck",
      "x": 224.62351179122925,
      "y": 107.80547738075256,
      "confidence": 0.9999912977218628
    },
    {
      "name": "left_shoulder",
      "x": 264.7189722061157,
      "y": 107.14433240890503,
      "confidence": 0.999996542930603
    },
    {
      "name": "right_shoulder",
      "x": 184.52805137634277,
      "y": 108.4666223526001,
      "confidence": 0.9999860525131226
    },
    {
      "name": "left_elbow",
      "x": 284.8798131942749,
      "y": 170.8409605026245,
      "confidence": 0.9957204461097717
    },
    {
      "name": "right_elbow",
      "x": 171.61625862121582,
      "y": 179.92633247375488,
      "confidence": 0.9747987389564514
    },
    {
      "name": "left_wrist",
      "x": 306.68225479125977,
      "y": 229.31179904937744,
      "confidence": 0.9972598552703857
    },
    {
      "name": "right_wrist",
      "x": 163.51643657684326,
      "y": 243.01496410369873,
      "confidence": 0.9873981475830078
    },
    {
      "name": "chest_center",
      "x": 224.62351179122925,
      "y": 169.18270635604858,
      "confidence": 0.9999932050704956
    },
    {
      "name": "waist_center",
      "x": 221.68300437927246,
      "y": 230.5599353313446,
      "confidence": 0.9999880194664001
    },
    {
      "name": "left_hip",
      "x": 244.02904891967773,
      "y": 231.12786531448364,
      "confidence": 0.9999898672103882
    },
    {
      "name": "right_hip",
      "x": 199.3369598388672,
      "y": 229.99200534820557,
      "confidence": 0.9999861717224121
    },
    {
      "name": "left_knee",
      "x": 249.97169971466064,
      "y": 331.2014284133911,
      "confidence": 0.9911224842071533
    },
    {
      "name": "right_knee",
      "x": 192.10291481018066,
      "y": 329.7472982406616,
      "confidence": 0.9870707392692566
    },
    {
      "name": "left_ankle",
      "x": 245.48376750946045,
      "y": 437.7961826324463,
      "confidence": 0.9959267973899841
    },
    {
      "name": "right_ankle",
      "x": 204.73287105560303,
      "y": 432.21159076690674,
      "confidence": 0.9952030181884766
    },
    {
      "name": "left_hand",
      "x": 305.69235038757324,
      "y": 248.51923084259033,
      "confidence": 0.994697093963623
    },
    {
      "name": "right_hand",
      "x": 165.44480895996094,
      "y": 262.7930679321289,
      "confidence": 0.9782295823097229
    },
    {
      "name": "left_foot",
      "x": 238.95526790618896,
      "y": 478.12743759155273,
      "confidence": 0.9954739212989807
    },
    {
      "name": "right_foot",
      "x": 191.07104969024658,
      "y": 469.0174388885498,
      "confidence": 0.9951170682907104
    }
  ],
  "confidence": 0.993409647661097,
  "image_width": 736,
  "image_height": 496,
  "keypoint_names": [
    "head_top",
    "head_center",
    "neck",
    "left_shoulder",
    "right_shoulder",
    "left_elbow",
    "right_elbow",
    "left_wrist",
    "right_wrist",
    "chest_center",
    "waist_center",
    "left_hip",
    "right_hip",
    "left_knee",
    "right_knee",
    "left_ankle",
    "right_ankle",
    "left_hand",
    "right_hand",
    "left_foot",
    "right_foot"
  ],
  "labeled_at": "2026-01-22T18:32:43.252188"
}