{
  "filename": "H_0797.jpg",
  "filepath": "anime_images/H_0797.jpg",
  "keypoints": [
    {
      "name": "head_top",
      "x": 578.9577484130859,
      "y": 1046.2085900306702,
      "confidence": 0.995470404624939
    },
    {
      "name": "head_center",
      "x": 578.9577484130859,
      "y": 1095.49147939682,
      "confidence": 0.995470404624939
    },
    {
      "name": "neck",
      "x": 595.6803917884827,
      "y": 1157.0950911045074,
      "confidence": 0.9993416965007782
    },
    {
      "name": "left_shoulder",
      "x": 621.782398223877,
      "y": 1161.2984863519669,
      "confidence": 0.9997852444648743
    },
    {
      "name": "right_shoulder",
      "x": 569.5783853530884,
      "y": 1152.891695857048,
      "confidence": 0.9988981485366821
    },
    {
      "name": "left_elbow",
      "x": 631.8878889083862,
      "y": 1310.6758863925934,
      "confidence": 0.539742648601532
    },
    {
      "name": "right_elbow",
      "x": 606.7405700683594,
      "y": 1284.4488911628723,
      "confidence": 0.021613093093037605
    },
    {
      "name": "left_wrist",
      "x": 618.7837600708008,
      "y": 1358.1348878145218,
      "confidence": 0.21184702217578888
    },
    {
      "name": "right_wrist",
      "x": 564.9997115135193,
      "y": 1371.410570859909,
      "confidence": 0.0285133458673954
    },
    {
      "name": "chest_center",
      "x": 595.6803917884827,
      "y": 1252.0271911919117,
      "confidence": 0.9997371733188629
    },
    {
      "name": "waist_center",
      "x": 600.4683494567871,
      "y": 1346.959291279316,
      "confidence": 0.9996430575847626
    },
    {
      "name": "left_hip",
      "x": 610.0362539291382,
      "y": 1357.411175608635,
      "confidence": 0.9996891021728516
    },
    {
      "name": "right_hip",
      "x": 590.900444984436,
      "y": 1336.507406949997,
      "confidence": 0.9995970129966736
    },
    {
      "name": "left_knee",
      "x": 620.9497690200806,
      "y": 1536.533705830574,
      "confidence": 0.6199861764907837
    },
    {
      "name": "right_knee",
      "x": 615.713381767273,
      "y": 1531.2454941272736,
      "confidence": 0.12093231081962585
    },
    {
      "name": "left_ankle",
      "x": 629.2391538619995,
      "y": 1716.2370961904526,
      "confidence": 0.818031907081604
    },
    {
      "name": "right_ankle",
      "x": 625.7960557937622,
      "y": 1710.3711391687393,
      "confidence": 0.46419453620910645
    },
    {
      "name": "left_hand",
      "x": 617.4478054046631,
      "y": 1373.329514503479,
      "confidence": 0.19253841042518616
    },
    {
      "name": "right_hand",
      "x": 560.2839231491089,
      "y": 1389.287271976471,
      "confidence": 0.03671092540025711
    },
    {
      "name": "left_foot",
      "x": 576.4617204666138,
      "y": 1749.6274244785309,
      "confidence": 0.766698956489563
    },
    {
      "name": "right_foot",
      "x": 567.9592967033386,
      "y": 1743.5549226999283,
      "confidence": 0.5296823382377625
    }
  ],
  "confidence": 0.5496430343345684,
  "image_width": 1200,
  "image_height": 1802,
  "keypoint_names": [
    "head_top",
    "head_center",
    "neck",
    "left_shoulder",
    "right_shoulder",
    "left_elbow",
    "right_elbow",
    "left_wrist",
    "right_wrist",
    "chest_center",
    "waist_center",
    "left_hip",
    "right_hip",
    "left_knee",
    "right_knee",
    "left_ankle",
    "right_ankle",
    "left_hand",
    "right_hand",
    "left_foot",
    "right_foot"
  ],
  "labeled_at": "2026-01-22T18:32:49.478844"
}