{
  "filename": "H_1080.jpg",
  "filepath": "anime_images/H_1080.jpg",
  "keypoints": [
    {
      "name": "head_top",
      "x": 253.66397324204445,
      "y": 12.165560275316238,
      "confidence": 0.9998600482940674
    },
    {
      "name": "head_center",
      "x": 253.66397324204445,
      "y": 85.75548455119133,
      "confidence": 0.9998600482940674
    },
    {
      "name": "neck",
      "x": 266.6807099580765,
      "y": 177.7428898960352,
      "confidence": 0.9999461770057678
    },
    {
      "name": "left_shoulder",
      "x": 337.58467549085617,
      "y": 176.19047313928604,
      "confidence": 0.9999644756317139
    },
    {
      "name": "right_shoulder",
      "x": 195.77674442529678,
      "y": 179.29530665278435,
      "confidence": 0.9999278783798218
    },
    {
      "name": "left_elbow",
      "x": 364.8998072743416,
      "y": 287.40646094083786,
      "confidence": 0.991940438747406
    },
    {
      "name": "right_elbow",
      "x": 165.43015322089195,
      "y": 286.9294196367264,
      "confidence": 0.9811042547225952
    },
    {
      "name": "left_wrist",
      "x": 371.95327389240265,
      "y": 391.8809086084366,
      "confidence": 0.9900726079940796
    },
    {
      "name": "right_wrist",
      "x": 146.786039352417,
      "y": 386.96260675787926,
      "confidence": 0.9926027655601501
    },
    {
      "name": "chest_center",
      "x": 266.6807099580765,
      "y": 282.4552634730935,
      "confidence": 0.9999694228172302
    },
    {
      "name": "waist_center",
      "x": 254.2820924371481,
      "y": 387.1676370501518,
      "confidence": 0.9999710917472839
    },
    {
      "name": "left_hip",
      "x": 292.01984691619873,
      "y": 387.5136733055115,
      "confidence": 0.9999743700027466
    },
    {
      "name": "right_hip",
      "x": 216.54433795809746,
      "y": 386.8216007947922,
      "confidence": 0.9999678134918213
    },
    {
      "name": "left_knee",
      "x": 319.9457907676697,
      "y": 542.6988080143929,
      "confidence": 0.9906278848648071
    },
    {
      "name": "right_knee",
      "x": 226.39082178473473,
      "y": 549.1807863116264,
      "confidence": 0.9750617146492004
    },
    {
      "name": "left_ankle",
      "x": 341.3351528644562,
      "y": 705.4873630404472,
      "confidence": 0.9944047927856445
    },
    {
      "name": "right_ankle",
      "x": 242.0154058933258,
      "y": 702.1896481513977,
      "confidence": 0.9892627596855164
    },
    {
      "name": "left_hand",
      "x": 365.3401476740837,
      "y": 424.87108409404755,
      "confidence": 0.9832674860954285
    },
    {
      "name": "right_hand",
      "x": 148.9071364402771,
      "y": 421.85907661914825,
      "confidence": 0.9871604442596436
    },
    {
      "name": "left_foot",
      "x": 373.2279523015022,
      "y": 760.1480647921562,
      "confidence": 0.9908705353736877
    },
    {
      "name": "right_foot",
      "x": 202.11120986938477,
      "y": 756.1455279588699,
      "confidence": 0.9839486479759216
    }
  ],
  "confidence": 0.9911775834420148,
  "image_width": 563,
  "image_height": 775,
  "keypoint_names": [
    "head_top",
    "head_center",
    "neck",
    "left_shoulder",
    "right_shoulder",
    "left_elbow",
    "right_elbow",
    "left_wrist",
    "right_wrist",
    "chest_center",
    "waist_center",
    "left_hip",
    "right_hip",
    "left_knee",
    "right_knee",
    "left_ankle",
    "right_ankle",
    "left_hand",
    "right_hand",
    "left_foot",
    "right_foot"
  ],
  "labeled_at": "2026-01-22T18:33:10.473648"
}