{
  "filename": "H_1937.jpg",
  "filepath": "human_images/H_1937.jpg",
  "keypoints": [
    {
      "name": "head_top",
      "x": 407.81604766845703,
      "y": 347.81004559993744,
      "confidence": 0.999901533126831
    },
    {
      "name": "head_center",
      "x": 407.81604766845703,
      "y": 353.68244326114655,
      "confidence": 0.999901533126831
    },
    {
      "name": "neck",
      "x": 421.95529556274414,
      "y": 361.02294033765793,
      "confidence": 0.9999775290489197
    },
    {
      "name": "left_shoulder",
      "x": 516.9003105163574,
      "y": 384.38925218582153,
      "confidence": 0.9999798536300659
    },
    {
      "name": "right_shoulder",
      "x": 327.01028060913086,
      "y": 337.6566284894943,
      "confidence": 0.9999752044677734
    },
    {
      "name": "left_elbow",
      "x": 529.0157051086426,
      "y": 538.8827469348907,
      "confidence": 0.9936122298240662
    },
    {
      "name": "right_elbow",
      "x": 280.75741958618164,
      "y": 469.9847710132599,
      "confidence": 0.9907427430152893
    },
    {
      "name": "left_wrist",
      "x": 524.8492450714111,
      "y": 670.7431511878967,
      "confidence": 0.9957007765769958
    },
    {
      "name": "right_wrist",
      "x": 235.94466876983643,
      "y": 604.3601796627045,
      "confidence": 0.9976085424423218
    },
    {
      "name": "chest_center",
      "x": 421.95529556274414,
      "y": 510.3432474732399,
      "confidence": 0.9999144673347473
    },
    {
      "name": "waist_center",
      "x": 389.9815697669983,
      "y": 659.6635546088219,
      "confidence": 0.9998563528060913
    },
    {
      "name": "left_hip",
      "x": 442.76903915405273,
      "y": 667.9010925292969,
      "confidence": 0.9998490810394287
    },
    {
      "name": "right_hip",
      "x": 337.19410037994385,
      "y": 651.4260166883469,
      "confidence": 0.9998636245727539
    },
    {
      "name": "left_knee",
      "x": 439.80774879455566,
      "y": 901.5196552276611,
      "confidence": 0.9791330695152283
    },
    {
      "name": "right_knee",
      "x": 285.265531539917,
      "y": 883.6504862308502,
      "confidence": 0.9842580556869507
    },
    {
      "name": "left_ankle",
      "x": 432.5371608734131,
      "y": 1132.1151294708252,
      "confidence": 0.981895387172699
    },
    {
      "name": "right_ankle",
      "x": 262.5586643218994,
      "y": 1118.0050964355469,
      "confidence": 0.9849158525466919
    },
    {
      "name": "left_hand",
      "x": 515.9824390411377,
      "y": 715.0764284133911,
      "confidence": 0.9920810461044312
    },
    {
      "name": "right_hand",
      "x": 230.74415016174316,
      "y": 652.8950711488724,
      "confidence": 0.9948981404304504
    },
    {
      "name": "left_foot",
      "x": 380.6229591369629,
      "y": 1204.8954226970673,
      "confidence": 0.9841566681861877
    },
    {
      "name": "right_foot",
      "x": 221.74950981140137,
      "y": 1190.4152998924255,
      "confidence": 0.9869564771652222
    }
  ],
  "confidence": 0.9920898991472581,
  "image_width": 736,
  "image_height": 1308,
  "keypoint_names": [
    "head_top",
    "head_center",
    "neck",
    "left_shoulder",
    "right_shoulder",
    "left_elbow",
    "right_elbow",
    "left_wrist",
    "right_wrist",
    "chest_center",
    "waist_center",
    "left_hip",
    "right_hip",
    "left_knee",
    "right_knee",
    "left_ankle",
    "right_ankle",
    "left_hand",
    "right_hand",
    "left_foot",
    "right_foot"
  ],
  "labeled_at": "2026-01-22T18:01:54.402595"
}