{
  "filename": "H_2248.jpg",
  "filepath": "human_images/H_2248.jpg",
  "keypoints": [
    {
      "name": "head_top",
      "x": 366.1214189529419,
      "y": 66.11960849761962,
      "confidence": 0.9998476505279541
    },
    {
      "name": "head_center",
      "x": 366.1214189529419,
      "y": 159.88552951812744,
      "confidence": 0.9998476505279541
    },
    {
      "name": "neck",
      "x": 363.8612103462219,
      "y": 277.0929307937622,
      "confidence": 0.9999640583992004
    },
    {
      "name": "left_shoulder",
      "x": 458.894193649292,
      "y": 276.71600818634033,
      "confidence": 0.999980092048645
    },
    {
      "name": "right_shoulder",
      "x": 268.82822704315186,
      "y": 277.4698534011841,
      "confidence": 0.9999480247497559
    },
    {
      "name": "left_elbow",
      "x": 480.16957092285156,
      "y": 433.2234477996826,
      "confidence": 0.9832406640052795
    },
    {
      "name": "right_elbow",
      "x": 249.39800262451172,
      "y": 433.05242443084717,
      "confidence": 0.9557808041572571
    },
    {
      "name": "left_wrist",
      "x": 481.9309997558594,
      "y": 566.9087104797363,
      "confidence": 0.9775897860527039
    },
    {
      "name": "right_wrist",
      "x": 249.65472412109375,
      "y": 572.1675310134888,
      "confidence": 0.9688881039619446
    },
    {
      "name": "chest_center",
      "x": 363.8612103462219,
      "y": 417.59552121162415,
      "confidence": 0.9999714493751526
    },
    {
      "name": "waist_center",
      "x": 365.6309084892273,
      "y": 558.0981116294861,
      "confidence": 0.9999573826789856
    },
    {
      "name": "left_hip",
      "x": 416.23973274230957,
      "y": 558.4516410827637,
      "confidence": 0.9999628067016602
    },
    {
      "name": "right_hip",
      "x": 315.022084236145,
      "y": 557.7445821762085,
      "confidence": 0.999951958656311
    },
    {
      "name": "left_knee",
      "x": 410.7877788543701,
      "y": 745.3496503829956,
      "confidence": 0.9659507274627686
    },
    {
      "name": "right_knee",
      "x": 317.9365882873535,
      "y": 750.5223999023438,
      "confidence": 0.8929173946380615
    },
    {
      "name": "left_ankle",
      "x": 409.27482414245605,
      "y": 946.3859424591064,
      "confidence": 0.9631240367889404
    },
    {
      "name": "right_ankle",
      "x": 325.5400323867798,
      "y": 954.7769451141357,
      "confidence": 0.9547305107116699
    },
    {
      "name": "left_hand",
      "x": 468.2798385620117,
      "y": 606.2398080825806,
      "confidence": 0.967670202255249
    },
    {
      "name": "right_hand",
      "x": 257.47547340393066,
      "y": 611.1738224029541,
      "confidence": 0.9554888010025024
    },
    {
      "name": "left_foot",
      "x": 409.05407524108887,
      "y": 1021.4072942733765,
      "confidence": 0.9637554883956909
    },
    {
      "name": "right_foot",
      "x": 313.5593156814575,
      "y": 1020.2188167572021,
      "confidence": 0.9430883526802063
    }
  ],
  "confidence": 0.9701126708703882,
  "image_width": 736,
  "image_height": 1104,
  "keypoint_names": [
    "head_top",
    "head_center",
    "neck",
    "left_shoulder",
    "right_shoulder",
    "left_elbow",
    "right_elbow",
    "left_wrist",
    "right_wrist",
    "chest_center",
    "waist_center",
    "left_hip",
    "right_hip",
    "left_knee",
    "right_knee",
    "left_ankle",
    "right_ankle",
    "left_hand",
    "right_hand",
    "left_foot",
    "right_foot"
  ],
  "labeled_at": "2026-01-22T18:00:49.020427"
}