{
  "filename": "H_2350.jpg",
  "filepath": "human_images/H_2350.jpg",
  "keypoints": [
    {
      "name": "head_top",
      "x": 377.09527587890625,
      "y": 133.98954916000366,
      "confidence": 0.9992437362670898
    },
    {
      "name": "head_center",
      "x": 377.09527587890625,
      "y": 185.6246781349182,
      "confidence": 0.9992437362670898
    },
    {
      "name": "neck",
      "x": 370.3810238838196,
      "y": 250.1685893535614,
      "confidence": 0.9998751580715179
    },
    {
      "name": "left_shoulder",
      "x": 431.50062370300293,
      "y": 251.3618540763855,
      "confidence": 0.9997839331626892
    },
    {
      "name": "right_shoulder",
      "x": 309.26142406463623,
      "y": 248.9753246307373,
      "confidence": 0.9999663829803467
    },
    {
      "name": "left_elbow",
      "x": 437.87720489501953,
      "y": 358.2296347618103,
      "confidence": 0.5786320567131042
    },
    {
      "name": "right_elbow",
      "x": 290.2546453475952,
      "y": 358.6733150482178,
      "confidence": 0.9827331304550171
    },
    {
      "name": "left_wrist",
      "x": 447.9205780029297,
      "y": 443.9759635925293,
      "confidence": 0.29803943634033203
    },
    {
      "name": "right_wrist",
      "x": 289.5294246673584,
      "y": 449.689382314682,
      "confidence": 0.9923900961875916
    },
    {
      "name": "chest_center",
      "x": 370.3810238838196,
      "y": 353.1154668331146,
      "confidence": 0.9998641312122345
    },
    {
      "name": "waist_center",
      "x": 368.5294442176819,
      "y": 456.06234431266785,
      "confidence": 0.9999596476554871
    },
    {
      "name": "left_hip",
      "x": 403.65880012512207,
      "y": 456.71881675720215,
      "confidence": 0.9999443292617798
    },
    {
      "name": "right_hip",
      "x": 333.4000883102417,
      "y": 455.40587186813354,
      "confidence": 0.9999749660491943
    },
    {
      "name": "left_knee",
      "x": 411.957239151001,
      "y": 611.4313554763794,
      "confidence": 0.9571403861045837
    },
    {
      "name": "right_knee",
      "x": 340.3252296447754,
      "y": 611.0628008842468,
      "confidence": 0.9446282982826233
    },
    {
      "name": "left_ankle",
      "x": 408.9974842071533,
      "y": 755.7322406768799,
      "confidence": 0.9689428210258484
    },
    {
      "name": "right_ankle",
      "x": 350.4435968399048,
      "y": 749.2752695083618,
      "confidence": 0.951948881149292
    },
    {
      "name": "left_hand",
      "x": 449.8677043914795,
      "y": 474.2071461677551,
      "confidence": 0.30259478092193604
    },
    {
      "name": "right_hand",
      "x": 298.41046619415283,
      "y": 481.90325260162354,
      "confidence": 0.9856919646263123
    },
    {
      "name": "left_foot",
      "x": 401.63946533203125,
      "y": 821.6287708282471,
      "confidence": 0.958304226398468
    },
    {
      "name": "right_foot",
      "x": 362.6106472015381,
      "y": 818.8383722305298,
      "confidence": 0.9236741065979004
    }
  ],
  "confidence": 0.8731549136778888,
  "image_width": 736,
  "image_height": 920,
  "keypoint_names": [
    "head_top",
    "head_center",
    "neck",
    "left_shoulder",
    "right_shoulder",
    "left_elbow",
    "right_elbow",
    "left_wrist",
    "right_wrist",
    "chest_center",
    "waist_center",
    "left_hip",
    "right_hip",
    "left_knee",
    "right_knee",
    "left_ankle",
    "right_ankle",
    "left_hand",
    "right_hand",
    "left_foot",
    "right_foot"
  ],
  "labeled_at": "2026-01-22T18:00:26.446857"
}