{
  "filename": "H_2532.jpg",
  "filepath": "human_images/H_2532.jpg",
  "keypoints": [
    {
      "name": "head_top",
      "x": 354.991322517395,
      "y": 248.52808552980423,
      "confidence": 0.9995548129081726
    },
    {
      "name": "head_center",
      "x": 354.991322517395,
      "y": 308.29738837480545,
      "confidence": 0.9995548129081726
    },
    {
      "name": "neck",
      "x": 312.97167921066284,
      "y": 383.009016931057,
      "confidence": 0.99996417760849
    },
    {
      "name": "left_shoulder",
      "x": 403.2347183227539,
      "y": 380.50732469558716,
      "confidence": 0.9999889135360718
    },
    {
      "name": "right_shoulder",
      "x": 222.70864009857178,
      "y": 385.5107091665268,
      "confidence": 0.9999394416809082
    },
    {
      "name": "left_elbow",
      "x": 439.91514015197754,
      "y": 494.22947108745575,
      "confidence": 0.909767210483551
    },
    {
      "name": "right_elbow",
      "x": 205.56135940551758,
      "y": 509.9998015165329,
      "confidence": 0.9408029913902283
    },
    {
      "name": "left_wrist",
      "x": 457.1448287963867,
      "y": 584.6802449226379,
      "confidence": 0.9651739001274109
    },
    {
      "name": "right_wrist",
      "x": 214.83772659301758,
      "y": 603.3416726589203,
      "confidence": 0.9605993032455444
    },
    {
      "name": "chest_center",
      "x": 312.97167921066284,
      "y": 506.07895106077194,
      "confidence": 0.9999611973762512
    },
    {
      "name": "waist_center",
      "x": 341.48980951309204,
      "y": 629.1488851904869,
      "confidence": 0.9999096989631653
    },
    {
      "name": "left_hip",
      "x": 389.30104064941406,
      "y": 626.9896059036255,
      "confidence": 0.9999334812164307
    },
    {
      "name": "right_hip",
      "x": 293.67857837677,
      "y": 631.3081644773483,
      "confidence": 0.9998859167098999
    },
    {
      "name": "left_knee",
      "x": 414.6712837219238,
      "y": 813.5040907859802,
      "confidence": 0.7102044820785522
    },
    {
      "name": "right_knee",
      "x": 302.67065238952637,
      "y": 815.4609589576721,
      "confidence": 0.6116482615470886
    },
    {
      "name": "left_ankle",
      "x": 417.6313896179199,
      "y": 993.3157954216003,
      "confidence": 0.7083020806312561
    },
    {
      "name": "right_ankle",
      "x": 332.48745918273926,
      "y": 987.5019478797913,
      "confidence": 0.6926872730255127
    },
    {
      "name": "left_hand",
      "x": 456.4546813964844,
      "y": 612.1949028968811,
      "confidence": 0.9557806849479675
    },
    {
      "name": "right_hand",
      "x": 228.9292449951172,
      "y": 628.7181208133698,
      "confidence": 0.9564296007156372
    },
    {
      "name": "left_foot",
      "x": 460.82500076293945,
      "y": 1039.730993270874,
      "confidence": 0.7569466829299927
    },
    {
      "name": "right_foot",
      "x": 319.9223852157593,
      "y": 1035.8724546432495,
      "confidence": 0.6970133185386658
    }
  ],
  "confidence": 0.8743916679831112,
  "image_width": 736,
  "image_height": 1308,
  "keypoint_names": [
    "head_top",
    "head_center",
    "neck",
    "left_shoulder",
    "right_shoulder",
    "left_elbow",
    "right_elbow",
    "left_wrist",
    "right_wrist",
    "chest_center",
    "waist_center",
    "left_hip",
    "right_hip",
    "left_knee",
    "right_knee",
    "left_ankle",
    "right_ankle",
    "left_hand",
    "right_hand",
    "left_foot",
    "right_foot"
  ],
  "labeled_at": "2026-01-22T18:00:29.640076"
}