{
  "filename": "H_2803.jpg",
  "filepath": "human_images/H_2803.jpg",
  "keypoints": [
    {
      "name": "head_top",
      "x": 399.8821020126343,
      "y": 45.28264045715332,
      "confidence": 0.9995571970939636
    },
    {
      "name": "head_center",
      "x": 399.8821020126343,
      "y": 141.07006788253784,
      "confidence": 0.9995571970939636
    },
    {
      "name": "neck",
      "x": 399.57042932510376,
      "y": 260.8043521642685,
      "confidence": 0.9999616146087646
    },
    {
      "name": "left_shoulder",
      "x": 501.50146484375,
      "y": 256.58780336380005,
      "confidence": 0.9999721050262451
    },
    {
      "name": "right_shoulder",
      "x": 297.6393938064575,
      "y": 265.02090096473694,
      "confidence": 0.9999511241912842
    },
    {
      "name": "left_elbow",
      "x": 540.2886867523193,
      "y": 426.3895511627197,
      "confidence": 0.9620805978775024
    },
    {
      "name": "right_elbow",
      "x": 271.86312675476074,
      "y": 445.0876235961914,
      "confidence": 0.977169930934906
    },
    {
      "name": "left_wrist",
      "x": 554.5628070831299,
      "y": 583.4242701530457,
      "confidence": 0.9667769074440002
    },
    {
      "name": "right_wrist",
      "x": 268.20220947265625,
      "y": 605.5822134017944,
      "confidence": 0.9886502027511597
    },
    {
      "name": "chest_center",
      "x": 399.57042932510376,
      "y": 425.8528992533684,
      "confidence": 0.9999504089355469
    },
    {
      "name": "waist_center",
      "x": 410.44232845306396,
      "y": 590.9014463424683,
      "confidence": 0.9999324083328247
    },
    {
      "name": "left_hip",
      "x": 468.6967372894287,
      "y": 589.2990589141846,
      "confidence": 0.9999287128448486
    },
    {
      "name": "right_hip",
      "x": 352.1879196166992,
      "y": 592.503833770752,
      "confidence": 0.9999361038208008
    },
    {
      "name": "left_knee",
      "x": 452.6876926422119,
      "y": 833.7568759918213,
      "confidence": 0.8668422698974609
    },
    {
      "name": "right_knee",
      "x": 372.667932510376,
      "y": 836.335301399231,
      "confidence": 0.9316279292106628
    },
    {
      "name": "left_ankle",
      "x": 422.15023040771484,
      "y": 1011.9094848632812,
      "confidence": 0.853680431842804
    },
    {
      "name": "right_ankle",
      "x": 387.4184846878052,
      "y": 1052.2172927856445,
      "confidence": 0.9538917541503906
    },
    {
      "name": "left_hand",
      "x": 551.0443687438965,
      "y": 631.8014860153198,
      "confidence": 0.9551589488983154
    },
    {
      "name": "right_hand",
      "x": 277.08303928375244,
      "y": 656.7606925964355,
      "confidence": 0.9827070832252502
    },
    {
      "name": "left_foot",
      "x": 416.1774158477783,
      "y": 1103.5842418670654,
      "confidence": 0.8487903475761414
    },
    {
      "name": "right_foot",
      "x": 388.2434606552124,
      "y": 1140.9599304199219,
      "confidence": 0.9271063804626465
    }
  ],
  "confidence": 0.9537545898381401,
  "image_width": 800,
  "image_height": 1200,
  "keypoint_names": [
    "head_top",
    "head_center",
    "neck",
    "left_shoulder",
    "right_shoulder",
    "left_elbow",
    "right_elbow",
    "left_wrist",
    "right_wrist",
    "chest_center",
    "waist_center",
    "left_hip",
    "right_hip",
    "left_knee",
    "right_knee",
    "left_ankle",
    "right_ankle",
    "left_hand",
    "right_hand",
    "left_foot",
    "right_foot"
  ],
  "labeled_at": "2026-01-22T18:00:48.269197"
}