{
  "filename": "H_2960.jpg",
  "filepath": "human_images/H_2960.jpg",
  "keypoints": [
    {
      "name": "head_top",
      "x": 384.9593549966812,
      "y": 99.78435039520264,
      "confidence": 0.9999947547912598
    },
    {
      "name": "head_center",
      "x": 384.9593549966812,
      "y": 167.1108603477478,
      "confidence": 0.9999947547912598
    },
    {
      "name": "neck",
      "x": 392.14206486940384,
      "y": 251.26899778842926,
      "confidence": 0.9999868869781494
    },
    {
      "name": "left_shoulder",
      "x": 462.0448797941208,
      "y": 251.7542839050293,
      "confidence": 0.9999915361404419
    },
    {
      "name": "right_shoulder",
      "x": 322.2392499446869,
      "y": 250.78371167182922,
      "confidence": 0.9999822378158569
    },
    {
      "name": "left_elbow",
      "x": 480.71520030498505,
      "y": 371.11443281173706,
      "confidence": 0.9942223429679871
    },
    {
      "name": "right_elbow",
      "x": 302.04910039901733,
      "y": 372.1623718738556,
      "confidence": 0.9863418936729431
    },
    {
      "name": "left_wrist",
      "x": 494.5102035999298,
      "y": 480.61782121658325,
      "confidence": 0.9934362173080444
    },
    {
      "name": "right_wrist",
      "x": 272.3630592226982,
      "y": 483.60276222229004,
      "confidence": 0.99037104845047
    },
    {
      "name": "chest_center",
      "x": 392.14206486940384,
      "y": 356.6676154732704,
      "confidence": 0.9999768733978271
    },
    {
      "name": "waist_center",
      "x": 387.35707104206085,
      "y": 462.0662331581116,
      "confidence": 0.9999634623527527
    },
    {
      "name": "left_hip",
      "x": 431.4965307712555,
      "y": 462.73523569107056,
      "confidence": 0.9999622106552124
    },
    {
      "name": "right_hip",
      "x": 343.2176113128662,
      "y": 461.3972306251526,
      "confidence": 0.999964714050293
    },
    {
      "name": "left_knee",
      "x": 418.67803037166595,
      "y": 647.2952961921692,
      "confidence": 0.9833805561065674
    },
    {
      "name": "right_knee",
      "x": 359.0284064412117,
      "y": 647.9505896568298,
      "confidence": 0.9744752049446106
    },
    {
      "name": "left_ankle",
      "x": 407.84141421318054,
      "y": 823.2395648956299,
      "confidence": 0.9824122786521912
    },
    {
      "name": "right_ankle",
      "x": 371.1002469062805,
      "y": 824.2264986038208,
      "confidence": 0.9803268909454346
    },
    {
      "name": "left_hand",
      "x": 492.44436621665955,
      "y": 516.3613557815552,
      "confidence": 0.9878438711166382
    },
    {
      "name": "right_hand",
      "x": 271.92655205726624,
      "y": 519.6211338043213,
      "confidence": 0.9815475940704346
    },
    {
      "name": "left_foot",
      "x": 399.4695693254471,
      "y": 867.6978945732117,
      "confidence": 0.9822577834129333
    },
    {
      "name": "right_foot",
      "x": 365.0783970952034,
      "y": 867.9330348968506,
      "confidence": 0.9768884778022766
    }
  ],
  "confidence": 0.9890235066413879,
  "image_width": 750,
  "image_height": 1000,
  "keypoint_names": [
    "head_top",
    "head_center",
    "neck",
    "left_shoulder",
    "right_shoulder",
    "left_elbow",
    "right_elbow",
    "left_wrist",
    "right_wrist",
    "chest_center",
    "waist_center",
    "left_hip",
    "right_hip",
    "left_knee",
    "right_knee",
    "left_ankle",
    "right_ankle",
    "left_hand",
    "right_hand",
    "left_foot",
    "right_foot"
  ],
  "labeled_at": "2026-01-22T18:01:46.278350"
}